LICENSE
MANIFEST.in
README.rst
setup.py
autocode/__init__.py
autocode/__main__.py
autocode/autocode.py
autocode/run.py
autocode.egg-info/PKG-INFO
autocode.egg-info/SOURCES.txt
autocode.egg-info/dependency_links.txt
autocode.egg-info/entry_points.txt
autocode.egg-info/top_level.txt