Metadata-Version: 1.0
Name: autocode
Version: 0.0.1
Summary: Python command line application bare bones template.
Home-page: http://gehrcke.de/2014/02/distributing-a-python-command-line-application
Author: Mehul Ahuja (hashcode55)
Author-email: blackdragon0909@gmail.com
License: UNKNOWN
Platform: UNKNOWN
